toml_to_requirements/__init__.py
toml_to_requirements/cli.py
toml_to_requirements/convert_toml_to_requirements.py
toml_to_requirements/main.py
toml_to_requirements/py.typed
toml_to_requirements-0.3.0.dist-info/METADATA
toml_to_requirements-0.3.0.dist-info/WHEEL
toml_to_requirements-0.3.0.dist-info/entry_points.txt
toml_to_requirements-0.3.0.dist-info/RECORD
