Metadata-Version: 2.1
Name: toml_to_requirements
Version: 0.3.0
Summary: Convert a pyproject.toml file to a requirements.txt file
License: MIT
Keywords: toml,requirements,converter,parser
Author: Jake Cyr
Author-email: cyrjake@gmail.com
Requires-Python: >=3.9,<=3.12
Classifier: Intended Audience :: Developers
Classifier: License :: OSI Approved :: MIT License
Classifier: Programming Language :: Python :: 3
Classifier: Programming Language :: Python :: 3.9
Classifier: Programming Language :: Python :: 3.10
Classifier: Programming Language :: Python :: 3.11
Classifier: Programming Language :: Python :: 3.12
Requires-Dist: toml (>=0.10.2,<0.11.0)
